manik_missingdata/MissingData.py
manik_missingdata-1.0.3.dist-info/LICENSE.txt
manik_missingdata-1.0.3.dist-info/METADATA
manik_missingdata-1.0.3.dist-info/WHEEL
manik_missingdata-1.0.3.dist-info/entry_points.txt
manik_missingdata-1.0.3.dist-info/top_level.txt
manik_missingdata-1.0.3.dist-info/RECORD
