Metadata-Version: 2.1
Name: manik-missingdata
Version: 1.0.3
Summary: Technique for handling missing data.
Home-page: https://github.com/manikmangla9/missingdata
Author: manik mangla
Author-email: manikmangla9@gmail.com
License: MIT
Platform: UNKNOWN
Classifier: License :: OSI Approved :: MIT License
Classifier: Programming Language :: Python :: 3
Classifier: Programming Language :: Python :: 3.7
Classifier: Programming Language :: Python :: 2.7
Requires-Dist: pandas
Requires-Dist: numpy
